eclipsera/__init__.py
eclipsera/__version__.py
eclipsera/py.typed
eclipsera/automl/__init__.py
eclipsera/automl/_auto_classifier.py
eclipsera/automl/_auto_regressor.py
eclipsera/cli/__init__.py
eclipsera/cli/main.py
eclipsera/cluster/__init__.py
eclipsera/cluster/_dbscan.py
eclipsera/cluster/_gaussian_mixture.py
eclipsera/cluster/_hierarchical.py
eclipsera/cluster/_kmeans.py
eclipsera/cluster/_mean_shift.py
eclipsera/cluster/_spectral.py
eclipsera/core/__init__.py
eclipsera/core/base.py
eclipsera/core/exceptions.py
eclipsera/core/metrics.py
eclipsera/core/utils.py
eclipsera/core/validation.py
eclipsera/decomposition/__init__.py
eclipsera/decomposition/_nmf.py
eclipsera/decomposition/_pca.py
eclipsera/decomposition/_truncated_svd.py
eclipsera/explainability/__init__.py
eclipsera/explainability/_feature_importance.py
eclipsera/explainability/_partial_dependence.py
eclipsera/explainability/_permutation_importance.py
eclipsera/feature_selection/__init__.py
eclipsera/feature_selection/_rfe.py
eclipsera/feature_selection/_univariate.py
eclipsera/feature_selection/_variance.py
eclipsera/manifold/__init__.py
eclipsera/manifold/_isomap.py
eclipsera/manifold/_lle.py
eclipsera/manifold/_tsne.py
eclipsera/ml/__init__.py
eclipsera/ml/ensemble.py
eclipsera/ml/linear.py
eclipsera/ml/naive_bayes.py
eclipsera/ml/neighbors.py
eclipsera/ml/neural_network.py
eclipsera/ml/svm.py
eclipsera/ml/tree.py
eclipsera/model_selection/__init__.py
eclipsera/model_selection/_search.py
eclipsera/model_selection/_split.py
eclipsera/pipeline/__init__.py
eclipsera/pipeline/_pipeline.py
eclipsera/preprocessing/__init__.py
eclipsera/preprocessing/encoders.py
eclipsera/preprocessing/imputation.py
eclipsera/preprocessing/scaling.py
eclipsera-1.1.0.dist-info/licenses/LICENSE
eclipsera-1.1.0.dist-info/METADATA
eclipsera-1.1.0.dist-info/WHEEL
eclipsera-1.1.0.dist-info/entry_points.txt
eclipsera-1.1.0.dist-info/top_level.txt
eclipsera-1.1.0.dist-info/RECORD
