Metadata-Version: 2.4
Name: eclipsera
Version: 1.1.0
Summary: A comprehensive machine learning framework with 68 algorithms spanning classical ML, clustering, AutoML, and explainability
Author-email: Eshan Roy <eshanized@proton.me>
Maintainer-email: Eshan Roy <eshanized@proton.me>
License: MIT
Project-URL: Homepage, https://github.com/TIVerse/eclipsera
Project-URL: Repository, https://github.com/TIVerse/eclipsera
Project-URL: Issues, https://github.com/TIVerse/eclipsera/issues
Project-URL: Changelog, https://github.com/TIVerse/eclipsera/blob/master/docs/changelog.rst
Keywords: machine-learning,automl,explainability,clustering,scikit-learn,dimensionality-reduction,manifold-learning,feature-selection,preprocessing,classification,regression
Classifier: Development Status :: 4 - Beta
Classifier: Intended Audience :: Developers
Classifier: Intended Audience :: Science/Research
Classifier: License :: OSI Approved :: MIT License
Classifier: Operating System :: OS Independent
Classifier: Programming Language :: Python :: 3
Classifier: Programming Language :: Python :: 3.8
Classifier: Programming Language :: Python :: 3.9
Classifier: Programming Language :: Python :: 3.10
Classifier: Programming Language :: Python :: 3.11
Classifier: Programming Language :: Python :: 3.12
Classifier: Programming Language :: Python :: 3.13
Classifier: Topic :: Scientific/Engineering :: Artificial Intelligence
Classifier: Topic :: Scientific/Engineering :: Information Analysis
Classifier: Topic :: Software Development :: Libraries :: Python Modules
Classifier: Typing :: Typed
Requires-Python: >=3.8
License-File: LICENSE
Requires-Dist: numpy>=1.20.0
Requires-Dist: scipy>=1.7.0
Provides-Extra: plot
Requires-Dist: matplotlib>=3.3.0; extra == "plot"
Provides-Extra: dev
Requires-Dist: pytest>=7.0; extra == "dev"
Requires-Dist: pytest-cov>=3.0; extra == "dev"
Requires-Dist: black>=22.0; extra == "dev"
Requires-Dist: isort>=5.10; extra == "dev"
Requires-Dist: mypy>=0.950; extra == "dev"
Requires-Dist: sphinx>=4.0; extra == "dev"
Requires-Dist: sphinx-rtd-theme>=1.0; extra == "dev"
Provides-Extra: all
Requires-Dist: matplotlib>=3.3.0; extra == "all"
Dynamic: license-file
